{"schema":1,"id":"memphis-mlgw","name":"Memphis Light, Gas & Water (MLGW)","adapter":"mlgw","collectedAt":1782906942597,"official":{"out":5,"served":427114,"nOut":5},"areas":[{"name":"Single Customer","out":1,"served":1,"etr":null,"loc":[35.11234,-89.80346],"subs":[],"eta":{"kind":"holding","label":"holding steady — no clear recovery yet","perHour":0}},{"name":"Single Customer","out":1,"served":1,"etr":null,"loc":[35.08961,-89.9255],"subs":[],"eta":{"kind":"holding","label":"holding steady — no clear recovery yet","perHour":0}},{"name":"Single Customer","out":1,"served":1,"etr":null,"loc":[35.05376,-90.03531],"subs":[],"eta":{"kind":"holding","label":"holding steady — no clear recovery yet","perHour":0}},{"name":"Single Customer","out":1,"served":1,"etr":null,"loc":[35.24375,-89.86347],"subs":[],"eta":{"kind":"holding","label":"holding steady — no clear recovery yet","perHour":0}},{"name":"Single Customer","out":1,"served":1,"etr":"07/01/2026 10:00:00 AM","loc":[34.99972,-90.05122],"subs":[],"eta":{"kind":"holding","label":"holding steady — no clear recovery yet","perHour":0}}]}