{"schema":1,"id":"orlando-ouc","name":"Orlando Utilities Commission (OUC)","adapter":"kubra","collectedAt":1782453853335,"official":{"out":4,"served":291524,"nOut":1},"areas":[{"name":"Orlando","out":0,"served":229799,"etr":null,"loc":[28.48162259250006,-81.23890052649995],"subs":[{"id":"Boun|Orlando|Orlando Southeast|quad","name":"Orlando Southeast","out":0,"served":86305,"etr":null,"loc":[28.44539050450004,-81.17242652599995]},{"id":"Boun|Orlando|Orlando Southwest|quad","name":"Orlando Southwest","out":0,"served":78108,"etr":null,"loc":[28.479544704000034,-81.44653367249995]},{"id":"Boun|Orlando|Orlando Northwest|quad","name":"Orlando Northwest","out":0,"served":37510,"etr":null,"loc":[28.578155692000053,-81.43093285399996]},{"id":"Boun|Orlando|Orlando Northeast|quad","name":"Orlando Northeast","out":0,"served":27876,"etr":null,"loc":[28.564244246000044,-81.33161825799996]}]},{"name":"St. Cloud","out":4,"served":61725,"etr":"2026-06-26T09:30:00Z","loc":[28.221420281000036,-81.21115197899996],"subs":[{"id":"Boun|St. Cloud|St. Cloud Northwest|quad","name":"St. Cloud Northwest","out":4,"served":14414,"etr":"2026-06-26T09:30:00Z","loc":[28.324313903000046,-81.29878052549995]},{"id":"Boun|St. Cloud|St. Cloud Southwest|quad","name":"St. Cloud Southwest","out":0,"served":20038,"etr":null,"loc":[28.208448297000047,-81.31113270999995]},{"id":"Boun|St. Cloud|St. Cloud Southeast|quad","name":"St. Cloud Southeast","out":0,"served":7977,"etr":null,"loc":[28.14344148750004,-81.14387221199996]},{"id":"Boun|St. Cloud|St. Cloud Northeast|quad","name":"St. Cloud Northeast","out":0,"served":19296,"etr":null,"loc":[28.324342072000036,-81.16817021949996]}]}]}