{"schema":1,"id":"sdge","name":"San Diego Gas & Electric (CA)","adapter":"kubra","collectedAt":1782959623348,"official":{"out":1317,"served":1547435,"nOut":2},"areas":[{"name":"91950","out":918,"served":20506,"etr":"2026-07-02T04:00:00Z","loc":[32.67508,-117.08898],"subs":[],"eta":{"kind":"holding","label":"holding steady — no clear recovery yet","perHour":0}},{"name":"92111","out":13,"served":23716,"etr":"ETR-EXP","loc":[32.80019,-117.17204],"subs":[],"eta":{"kind":"holding","label":"holding steady — no clear recovery yet","perHour":0}},{"name":"92139","out":386,"served":11416,"etr":"2026-07-02T04:00:00Z","loc":[32.68007,-117.04712],"subs":[],"eta":{"kind":"holding","label":"holding steady — no clear recovery yet","perHour":0}}]}