{"schema":1,"id":"vectren-indiana","name":"CenterPoint/Vectren — Southern Indiana","adapter":"datacapable","collectedAt":1782882241628,"official":{"out":9,"served":151007,"nOut":3},"areas":[{"name":"6084197","out":7,"served":7,"etr":"2026-07-01T08:02:56.000Z","loc":[38.06341,-87.10712],"subs":[],"eta":{"kind":"holding","label":"holding steady — no clear recovery yet","perHour":0}},{"name":"6084202","out":1,"served":1,"etr":"2026-07-01T07:21:19.000Z","loc":[37.99509,-87.64718],"subs":[],"eta":{"kind":"holding","label":"holding steady — no clear recovery yet","perHour":0}},{"name":"6084208","out":1,"served":1,"etr":"2026-07-01T05:30:00.000Z","loc":[37.99888,-87.492],"subs":[],"eta":{"kind":"holding","label":"holding steady — no clear recovery yet","perHour":0}}]}