{"schema":1,"id":"volunteer-energy","name":"Volunteer Energy Coop (TN)","adapter":"kiuc","collectedAt":1782930898578,"official":{"out":70,"served":132289,"nOut":5},"areas":[{"name":"37854","out":0,"served":327,"etr":null,"loc":null,"subs":[]},{"name":"37766","out":0,"served":1,"etr":null,"loc":null,"subs":[]},{"name":"37932","out":0,"served":1,"etr":null,"loc":null,"subs":[]},{"name":"37353","out":0,"served":1594,"etr":null,"loc":null,"subs":[]},{"name":"37322","out":0,"served":5485,"etr":null,"loc":null,"subs":[]},{"name":"37308","out":0,"served":1695,"etr":null,"loc":null,"subs":[]},{"name":"37321","out":0,"served":69,"etr":null,"loc":null,"subs":[]},{"name":"38558","out":0,"served":6572,"etr":null,"loc":null,"subs":[]},{"name":"37774","out":0,"served":200,"etr":null,"loc":null,"subs":[]},{"name":"38574","out":62,"served":5063,"etr":null,"loc":null,"subs":[],"eta":{"kind":"collecting","label":"estimating… (need another reading)"}},{"name":"37332","out":0,"served":1386,"etr":null,"loc":null,"subs":[]},{"name":"30710","out":0,"served":1,"etr":null,"loc":null,"subs":[]},{"name":"37243","out":0,"served":1,"etr":null,"loc":null,"subs":[]},{"name":"38557","out":0,"served":34,"etr":null,"loc":null,"subs":[]},{"name":"37336","out":0,"served":2541,"etr":null,"loc":null,"subs":[]},{"name":"38549","out":0,"served":3373,"etr":null,"loc":null,"subs":[]},{"name":"37402","out":0,"served":1,"etr":null,"loc":null,"subs":[]},{"name":"38556","out":0,"served":9334,"etr":null,"loc":null,"subs":[]},{"name":"37371","out":0,"served":11,"etr":null,"loc":null,"subs":[]},{"name":"37311","out":0,"served":1956,"etr":null,"loc":null,"subs":[]},{"name":"37316","out":0,"served":3,"etr":null,"loc":null,"subs":[]},{"name":"38553","out":0,"served":1686,"etr":null,"loc":null,"subs":[]},{"name":"37421","out":0,"served":1,"etr":null,"loc":null,"subs":[]},{"name":"38554","out":0,"served":714,"etr":null,"loc":null,"subs":[]},{"name":"37846","out":0,"served":601,"etr":null,"loc":null,"subs":[]},{"name":"37341","out":0,"served":4171,"etr":null,"loc":null,"subs":[]},{"name":"38583","out":0,"served":2456,"etr":null,"loc":null,"subs":[]},{"name":"37763","out":0,"served":2227,"etr":null,"loc":null,"subs":[]},{"name":"37329","out":0,"served":2,"etr":null,"loc":null,"subs":[]},{"name":"37370","out":0,"served":2707,"etr":null,"loc":null,"subs":[]},{"name":"37343","out":0,"served":2,"etr":null,"loc":null,"subs":[]},{"name":"37723","out":0,"served":852,"etr":null,"loc":null,"subs":[]},{"name":"37381","out":0,"served":6536,"etr":null,"loc":null,"subs":[]},{"name":"37921","out":0,"served":1,"etr":null,"loc":null,"subs":[]},{"name":"37880","out":0,"served":3035,"etr":null,"loc":null,"subs":[]},{"name":"37361","out":0,"served":1200,"etr":null,"loc":null,"subs":[]},{"name":"37331","out":0,"served":96,"etr":null,"loc":null,"subs":[]},{"name":"37315","out":0,"served":1,"etr":null,"loc":null,"subs":[]},{"name":"38571","out":1,"served":8063,"etr":null,"loc":null,"subs":[],"eta":{"kind":"holding","label":"holding steady — no clear recovery yet","perHour":0}},{"name":"(region)","out":0,"served":82,"etr":null,"loc":null,"subs":[]},{"name":"37357","out":0,"served":1,"etr":null,"loc":null,"subs":[]},{"name":"37307","out":0,"served":3136,"etr":null,"loc":null,"subs":[]},{"name":"37364","out":0,"served":35,"etr":null,"loc":null,"subs":[]},{"name":"38570","out":0,"served":1,"etr":null,"loc":null,"subs":[]},{"name":"37323","out":0,"served":6600,"etr":null,"loc":null,"subs":[]},{"name":"37367","out":0,"served":259,"etr":null,"loc":null,"subs":[]},{"name":"37310","out":0,"served":2519,"etr":null,"loc":null,"subs":[]},{"name":"37320","out":0,"served":96,"etr":null,"loc":null,"subs":[]},{"name":"38589","out":0,"served":318,"etr":null,"loc":null,"subs":[]},{"name":"37302","out":0,"served":34,"etr":null,"loc":null,"subs":[]},{"name":"37350","out":0,"served":1,"etr":null,"loc":null,"subs":[]},{"name":"38504","out":0,"served":828,"etr":null,"loc":null,"subs":[]},{"name":"37362","out":1,"served":2008,"etr":null,"loc":null,"subs":[],"eta":{"kind":"collecting","label":"estimating… (need another reading)"}},{"name":"37303","out":0,"served":4276,"etr":null,"loc":null,"subs":[]},{"name":"38578","out":0,"served":106,"etr":null,"loc":null,"subs":[]},{"name":"37826","out":0,"served":450,"etr":null,"loc":null,"subs":[]},{"name":"37312","out":1,"served":6370,"etr":null,"loc":null,"subs":[],"eta":{"kind":"collecting","label":"estimating… (need another reading)"}},{"name":"38555","out":0,"served":13995,"etr":null,"loc":null,"subs":[]},{"name":"38577","out":0,"served":839,"etr":null,"loc":null,"subs":[]},{"name":"38550","out":0,"served":1,"etr":null,"loc":null,"subs":[]},{"name":"37771","out":0,"served":1,"etr":null,"loc":null,"subs":[]},{"name":"37726","out":0,"served":116,"etr":null,"loc":null,"subs":[]},{"name":"37874","out":0,"served":56,"etr":null,"loc":null,"subs":[]},{"name":"37325","out":5,"served":654,"etr":null,"loc":null,"subs":[],"eta":{"kind":"collecting","label":"estimating… (need another reading)"}},{"name":"37309","out":0,"served":1385,"etr":null,"loc":null,"subs":[]},{"name":"37841","out":0,"served":1,"etr":null,"loc":null,"subs":[]},{"name":"37369","out":0,"served":747,"etr":null,"loc":null,"subs":[]},{"name":"37337","out":0,"served":1013,"etr":null,"loc":null,"subs":[]},{"name":"37363","out":0,"served":6195,"etr":null,"loc":null,"subs":[]},{"name":"37852","out":0,"served":13,"etr":null,"loc":null,"subs":[]},{"name":"38572","out":0,"served":7987,"etr":null,"loc":null,"subs":[]},{"name":"38565","out":0,"served":689,"etr":null,"loc":null,"subs":[]},{"name":"38501","out":0,"served":2,"etr":null,"loc":null,"subs":[]},{"name":"37405","out":0,"served":1,"etr":null,"loc":null,"subs":[]}]}