{"schema":1,"id":"wisconsin-public-service","name":"Wisconsin Public Service (WPS)","adapter":"wec","collectedAt":1782597448916,"official":{"out":5,"served":458948,"nOut":3},"areas":[{"name":"vilas","out":1,"served":20578,"etr":"Jun 27, 7:00 p.m.","loc":[45.95052,-89.53092],"subs":[{"id":"vilas|0","name":"saint germain","out":1,"served":3074,"etr":"Jun 27, 7:00 p.m.","loc":[45.95051864873304,-89.53092363861954]}]},{"name":"marinette","out":3,"served":32667,"etr":"Reassessing – Outage may require multiple crews. New ETR will post when necessary resources arrive on site to complete restoration.","loc":[45.31635,-88.18337],"subs":[{"id":"marinette|0","name":"stephenson","out":3,"served":5804,"etr":"Reassessing – Outage may require multiple crews. New ETR will post when necessary resources arrive on site to complete restoration.","loc":[45.31634885243505,-88.18337444457742]}]},{"name":"menominee","out":1,"served":9344,"etr":"Jun 27, 5:30 p.m.","loc":[45.31397,-87.66704],"subs":[{"id":"menominee|0","name":"mellen","out":1,"served":767,"etr":"Jun 27, 5:30 p.m.","loc":[45.31396838507372,-87.667044653384]}]}]}